setup.py
Flask_MetaRoute.egg-info/PKG-INFO
Flask_MetaRoute.egg-info/SOURCES.txt
Flask_MetaRoute.egg-info/dependency_links.txt
Flask_MetaRoute.egg-info/entry_points.txt
Flask_MetaRoute.egg-info/requires.txt
Flask_MetaRoute.egg-info/top_level.txt
Flask_MetaRoute.egg-info/zip-safe
flask_metaroute/__init__.py
flask_metaroute/decorators.py
flask_metaroute/func.py
flask_metaroute/metaroute.py
flask_metaroute/middleware.py