Metadata-Version: 1.1
Name: Flask-MetaRoute
Version: 1.3.0
Summary: Extra routing capabilities for Flask
Home-page: https://github.com/deep-orca/Flask-MetaRoute
Author: Orca
Author-email: deep.orca@gmail.com
License: BSD
Platform: any
Classifier: Development Status :: 4 - Beta
Classifier: Environment :: Web Environment
Classifier: Intended Audience :: Developers
Classifier: License :: OSI Approved :: BSD License
Classifier: Operating System :: OS Independent
Classifier: Programming Language :: Python
Classifier: Programming Language :: Python :: 3
Classifier: Topic :: Internet :: WWW/HTTP :: Dynamic Content
Classifier: Topic :: Software Development :: Libraries :: Python Modules
